nwon_django_toolbox/__init__.py
nwon_django_toolbox/admin/__init__.py
nwon_django_toolbox/admin/custom_titled_filter.py
nwon_django_toolbox/admin/hidden_fields_mixin.py
nwon_django_toolbox/admin/model_admin_with_json_editor.py
nwon_django_toolbox/admin/read_only_admin_mixin.py
nwon_django_toolbox/admin/read_only_inline.py
nwon_django_toolbox/admin/render_list_in_admin.py
nwon_django_toolbox/celery/__init__.py
nwon_django_toolbox/celery/memcache_lock.py
nwon_django_toolbox/exception_handler/__init__.py
nwon_django_toolbox/exception_handler/api_exception_handler.py
nwon_django_toolbox/exception_handler/exception_middleware.py
nwon_django_toolbox/exception_handler/get_error_response.py
nwon_django_toolbox/fields/__init__.py
nwon_django_toolbox/fields/file_field_base64.py
nwon_django_toolbox/fields/lower_case_email_field.py
nwon_django_toolbox/fields/pydantic_json_field/__init__.py
nwon_django_toolbox/fields/pydantic_json_field/model_serializer_with_pydantic.py
nwon_django_toolbox/fields/pydantic_json_field/pydantic_json_field.py
nwon_django_toolbox/fields/pydantic_json_field/pydantic_json_field_serializer.py
nwon_django_toolbox/fields/serializer_choice_field_for_polymorphic_ctype_id.py
nwon_django_toolbox/files/__init__.py
nwon_django_toolbox/files/temporary_file_from_url.py
nwon_django_toolbox/fixtures/__init__.py
nwon_django_toolbox/fixtures/dump_fixtures.py
nwon_django_toolbox/fixtures/load_fixtures.py
nwon_django_toolbox/fixtures/read_fixture_file.py
nwon_django_toolbox/helper/__init__.py
nwon_django_toolbox/helper/cleanup_duplicates.py
nwon_django_toolbox/models/__init__.py
nwon_django_toolbox/models/all_app_models.py
nwon_django_toolbox/models/base_model.py
nwon_django_toolbox/models/update_validation/__init__.py
nwon_django_toolbox/models/update_validation/allow_updates_for_model.py
nwon_django_toolbox/models/update_validation/validate_model_update.py
nwon_django_toolbox/nwon_django_settings.py
nwon_django_toolbox/permissions/__init__.py
nwon_django_toolbox-0.6.28.dist-info/METADATA
nwon_django_toolbox-0.6.28.dist-info/WHEEL
nwon_django_toolbox-0.6.28.dist-info/entry_points.txt
nwon_django_toolbox-0.6.28.dist-info/RECORD
