Metadata-Version: 2.3
Name: nwon_django_toolbox
Version: 0.6.28
Summary: Some Django Wizardry
License: MIT
Author: Reik Stiebeling
Author-email: reik.stiebeling@nwon.de
Requires-Python: >=3.10,<4.0
Classifier: License :: OSI Approved :: MIT License
Classifier: Programming Language :: Python :: 3
Classifier: Programming Language :: Python :: 3.10
Classifier: Programming Language :: Python :: 3.11
Classifier: Programming Language :: Python :: 3.12
Classifier: Programming Language :: Python :: 3.13
Requires-Dist: django (>=3.0)
Requires-Dist: django-json-widget (>=1.1.1,<2.0.0)
Requires-Dist: django-polymorphic (>=3.1.0,<4.0.0)
Requires-Dist: django-rest-polymorphic (>=0.1.9,<0.2.0)
Requires-Dist: drf-spectacular (>=0.22.0)
Requires-Dist: drf-yasg (>=1.20.0)
Requires-Dist: jsonschema-to-openapi (>=0.2.1,<0.3.0)
Requires-Dist: nwon-baseline (>=0.2.15,<0.3.0)
Requires-Dist: pillow (>=11.0.0)
Requires-Dist: pydantic (>=2.1.0)
Requires-Dist: pyhumps (>=3.0.2,<4.0.0)
Requires-Dist: pytest-factoryboy (>=2.7.0,<3.0.0)
